{
  "name": "Alpha+",
  "description": "By Orz-3",
  "icons": [
    {"name": "10000", "url": "https://raw.githubusercontent.com/Orz-3/mini/master/Alpha/10000.png"},
    {"name": "10010", "url": "https://raw.githubusercontent.com/Orz-3/mini/master/Alpha/10010.png"},
    {"name": "10086", "url": "https://raw.githubusercontent.com/Orz-3/mini/master/Alpha/10086.png"},
    {"name": "10086fee", "url": "https://raw.githubusercontent.com/Orz-3/mini/master/Alpha/10086fee.png"},
    {"name": "115", "url": "https://raw.githubusercontent.com/Orz-3/mini/master/Alpha/115.png"},
    {"name": "12306", "url": "https://raw.githubusercontent.com/Orz-3/mini/master/Alpha/12306.png"},
    {"name": "163GameVip", "url": "https://raw.githubusercontent.com/Orz-3/mini/master/Alpha/163GameVip.png"},
    {"name": "52pj", "url": "https://raw.githubusercontent.com/Orz-3/mini/master/Alpha/52pj.png"},
    {"name": "AAEX", "url": "https://raw.githubusercontent.com/Orz-3/mini/master/Alpha/AAEX.png"},
    {"name": "AE", "url": "https://raw.githubusercontent.com/Orz-3/mini/master/Alpha/AE.png"},
    {"name": "AEX", "url": "https://raw.githubusercontent.com/Orz-3/mini/master/Alpha/AEX.png"},
    {"name": "AR", "url": "https://raw.githubusercontent.com/Orz-3/mini/master/Alpha/AR.png"},
    {"name": "ASN", "url": "https://raw.githubusercontent.com/Orz-3/mini/master/Alpha/ASN.png"},
    {"name": "AU", "url": "https://raw.githubusercontent.com/Orz-3/mini/master/Alpha/AU.png"},
    {"name": "AWS", "url": "https://raw.githubusercontent.com/Orz-3/mini/master/Alpha/AWS.png"},
    {"name": "AZ", "url": "https://raw.githubusercontent.com/Orz-3/mini/master/Alpha/AZ.png"},
    {"name": "AbemaTV", "url": "https://raw.githubusercontent.com/Orz-3/mini/master/Alpha/AbemaTV.png"},
    {"name": "Advertising", "url": "https://raw.githubusercontent.com/Orz-3/mini/master/Alpha/Advertising.png"},
    {"name": "All-4", "url": "https://raw.githubusercontent.com/Orz-3/mini/master/Alpha/All-4.png"},
    {"name": "Amy", "url": "https://raw.githubusercontent.com/Orz-3/mini/master/Alpha/Amy.png"},
    {"name": "Apple", "url": "https://raw.githubusercontent.com/Orz-3/mini/master/Alpha/Apple.png"},
    {"name": "Ark", "url": "https://raw.githubusercontent.com/Orz-3/mini/master/Alpha/Ark.png"},
    {"name": "Azure", "url": "https://raw.githubusercontent.com/Orz-3/mini/master/Alpha/Azure.png"},
    {"name": "BBC-iPlayer", "url": "https://raw.githubusercontent.com/Orz-3/mini/master/Alpha/BBC-iPlayer.png"},
    {"name": "BG", "url": "https://raw.githubusercontent.com/Orz-3/mini/master/Alpha/BG.png"},
    {"name": "BGP", "url": "https://raw.githubusercontent.com/Orz-3/mini/master/Alpha/BGP.png"},
    {"name": "BR", "url": "https://raw.githubusercontent.com/Orz-3/mini/master/Alpha/BR.png"},
    {"name": "Bahamut", "url": "https://raw.githubusercontent.com/Orz-3/mini/master/Alpha/Bahamut.png"},
    {"name": "Bitcloud", "url": "https://raw.githubusercontent.com/Orz-3/mini/master/Alpha/Bitcloud.png"},
    {"name": "Blibee", "url": "https://raw.githubusercontent.com/Orz-3/mini/master/Alpha/Blibee.png"},
    {"name": "Blink", "url": "https://raw.githubusercontent.com/Orz-3/mini/master/Alpha/Blink.png"},
    {"name": "Boom", "url": "https://raw.githubusercontent.com/Orz-3/mini/master/Alpha/Boom.png"},
    {"name": "Boslife", "url": "https://raw.githubusercontent.com/Orz-3/mini/master/Alpha/Boslife.png"},
    {"name": "Bywave", "url": "https://raw.githubusercontent.com/Orz-3/mini/master/Alpha/Bywave.png"},
    {"name": "CA", "url": "https://raw.githubusercontent.com/Orz-3/mini/master/Alpha/CA.png"},
    {"name": "CCCat", "url": "https://raw.githubusercontent.com/Orz-3/mini/master/Alpha/CCCat.png"},
    {"name": "CH", "url": "https://raw.githubusercontent.com/Orz-3/mini/master/Alpha/CH.png"},
    {"name": "CN", "url": "https://raw.githubusercontent.com/Orz-3/mini/master/Alpha/CN.png"},
    {"name": "CNIX", "url": "https://raw.githubusercontent.com/Orz-3/mini/master/Alpha/CNIX.png"},
    {"name": "COVID-19", "url": "https://raw.githubusercontent.com/Orz-3/mini/master/Alpha/COVID-19.png"},
    {"name": "CZ", "url": "https://raw.githubusercontent.com/Orz-3/mini/master/Alpha/CZ.png"},
    {"name": "Catnet", "url": "https://raw.githubusercontent.com/Orz-3/mini/master/Alpha/Catnet.png"},
    {"name": "China", "url": "https://raw.githubusercontent.com/Orz-3/mini/master/Alpha/China.png"},
    {"name": "Cm", "url": "https://raw.githubusercontent.com/Orz-3/mini/master/Alpha/Cm.png"},
    {"name": "Coco", "url": "https://raw.githubusercontent.com/Orz-3/mini/master/Alpha/Coco.png"},
    {"name": "Cord", "url": "https://raw.githubusercontent.com/Orz-3/mini/master/Alpha/Cord.png"},
    {"name": "Cylink", "url": "https://raw.githubusercontent.com/Orz-3/mini/master/Alpha/Cylink.png"},
    {"name": "DAZN", "url": "https://raw.githubusercontent.com/Orz-3/mini/master/Alpha/DAZN.png"},
    {"name": "DE", "url": "https://raw.githubusercontent.com/Orz-3/mini/master/Alpha/DE.png"},
    {"name": "DLK", "url": "https://raw.githubusercontent.com/Orz-3/mini/master/Alpha/DLK.png"},
    {"name": "DMM", "url": "https://raw.githubusercontent.com/Orz-3/mini/master/Alpha/DMM.png"},
    {"name": "Deezer", "url": "https://raw.githubusercontent.com/Orz-3/mini/master/Alpha/Deezer.png"},
    {"name": "Dianliang", "url": "https://raw.githubusercontent.com/Orz-3/mini/master/Alpha/Dianliang.png"},
    {"name": "DisneyPlus", "url": "https://raw.githubusercontent.com/Orz-3/mini/master/Alpha/DisneyPlus.png"},
    {"name": "Dler", "url": "https://raw.githubusercontent.com/Orz-3/mini/master/Alpha/Dler.png"},
    {"name": "Domino", "url": "https://raw.githubusercontent.com/Orz-3/mini/master/Alpha/Domino.png"},
    {"name": "Duang", "url": "https://raw.githubusercontent.com/Orz-3/mini/master/Alpha/Duang.png"},
    {"name": "Dukou", "url": "https://raw.githubusercontent.com/Orz-3/mini/master/Alpha/Dukou.png"},
    {"name": "Element", "url": "https://raw.githubusercontent.com/Orz-3/mini/master/Alpha/Element.png"},
    {"name": "Enet", "url": "https://raw.githubusercontent.com/Orz-3/mini/master/Alpha/Enet.png"},
    {"name": "Enterprise", "url": "https://raw.githubusercontent.com/Orz-3/mini/master/Alpha/Enterprise.png"},
    {"name": "Exflux", "url": "https://raw.githubusercontent.com/Orz-3/mini/master/Alpha/Exflux.png"},
    {"name": "FNF", "url": "https://raw.githubusercontent.com/Orz-3/mini/master/Alpha/FNF.png"},
    {"name": "FOX-NOW", "url": "https://raw.githubusercontent.com/Orz-3/mini/master/Alpha/FOX-NOW.png"},
    {"name": "FOXPlus", "url": "https://raw.githubusercontent.com/Orz-3/mini/master/Alpha/FOXPlus.png"},
    {"name": "FR", "url": "https://raw.githubusercontent.com/Orz-3/mini/master/Alpha/FR.png"},
    {"name": "FRANXX", "url": "https://raw.githubusercontent.com/Orz-3/mini/master/Alpha/FRANXX.png"},
    {"name": "Fastfish", "url": "https://raw.githubusercontent.com/Orz-3/mini/master/Alpha/Fastfish.png"},
    {"name": "Fastlink", "url": "https://raw.githubusercontent.com/Orz-3/mini/master/Alpha/Fastlink.png"},
    {"name": "Fastnode", "url": "https://raw.githubusercontent.com/Orz-3/mini/master/Alpha/Fastnode.png"},
    {"name": "Final", "url": "https://raw.githubusercontent.com/Orz-3/mini/master/Alpha/Final.png"},
    {"name": "Flower", "url": "https://raw.githubusercontent.com/Orz-3/mini/master/Alpha/Flower.png"},
    {"name": "Flyint", "url": "https://raw.githubusercontent.com/Orz-3/mini/master/Alpha/Flyint.png"},
    {"name": "GCP", "url": "https://raw.githubusercontent.com/Orz-3/mini/master/Alpha/GCP.png"},
    {"name": "GLaDOS", "url": "https://raw.githubusercontent.com/Orz-3/mini/master/Alpha/GLaDOS.png"},
    {"name": "GaCloud", "url": "https://raw.githubusercontent.com/Orz-3/mini/master/Alpha/GaCloud.png"},
    {"name": "Global", "url": "https://raw.githubusercontent.com/Orz-3/mini/master/Alpha/Global.png"},
    {"name": "Godetia", "url": "https://raw.githubusercontent.com/Orz-3/mini/master/Alpha/Godetia.png"},
    {"name": "Google", "url": "https://raw.githubusercontent.com/Orz-3/mini/master/Alpha/Google.png"},
    {"name": "Guguex", "url": "https://raw.githubusercontent.com/Orz-3/mini/master/Alpha/Guguex.png"},
    {"name": "HBO-GO-HKG", "url": "https://raw.githubusercontent.com/Orz-3/mini/master/Alpha/HBO-GO-HKG.png"},
    {"name": "HBO", "url": "https://raw.githubusercontent.com/Orz-3/mini/master/Alpha/HBO.png"},
    {"name": "HK", "url": "https://raw.githubusercontent.com/Orz-3/mini/master/Alpha/HK.png"},
    {"name": "HU", "url": "https://raw.githubusercontent.com/Orz-3/mini/master/Alpha/HU.png"},
    {"name": "HWTV", "url": "https://raw.githubusercontent.com/Orz-3/mini/master/Alpha/HWTV.png"},
    {"name": "Hijacking", "url": "https://raw.githubusercontent.com/Orz-3/mini/master/Alpha/Hijacking.png"},
    {"name": "Hitun", "url": "https://raw.githubusercontent.com/Orz-3/mini/master/Alpha/Hitun.png"},
    {"name": "Hulu", "url": "https://raw.githubusercontent.com/Orz-3/mini/master/Alpha/Hulu.png"},
    {"name": "Hxlm", "url": "https://raw.githubusercontent.com/Orz-3/mini/master/Alpha/Hxlm.png"},
    {"name": "IE", "url": "https://raw.githubusercontent.com/Orz-3/mini/master/Alpha/IE.png"},
    {"name": "IEPL", "url": "https://raw.githubusercontent.com/Orz-3/mini/master/Alpha/IEPL.png"},
    {"name": "IN", "url": "https://raw.githubusercontent.com/Orz-3/mini/master/Alpha/IN.png"},
    {"name": "IPLC", "url": "https://raw.githubusercontent.com/Orz-3/mini/master/Alpha/IPLC.png"},
    {"name": "IT", "url": "https://raw.githubusercontent.com/Orz-3/mini/master/Alpha/IT.png"},
    {"name": "ITV", "url": "https://raw.githubusercontent.com/Orz-3/mini/master/Alpha/ITV.png"},
    {"name": "Imm", "url": "https://raw.githubusercontent.com/Orz-3/mini/master/Alpha/Imm.png"},
    {"name": "Instagram", "url": "https://raw.githubusercontent.com/Orz-3/mini/master/Alpha/Instagram.png"},
    {"name": "JOOX", "url": "https://raw.githubusercontent.com/Orz-3/mini/master/Alpha/JOOX.png"},
    {"name": "JP", "url": "https://raw.githubusercontent.com/Orz-3/mini/master/Alpha/JP.png"},
    {"name": "KKBOX", "url": "https://raw.githubusercontent.com/mini/master/Alpha/KKBOX.png"},
    {"name": "KKTV", "url": "https://raw.githubusercontent.com/Orz-3/mini/master/Alpha/KKTV.png"},
    {"name": "KR", "url": "https://raw.githubusercontent.com/Orz-3/mini/master/Alpha/KR.png"},
    {"name": "Kache", "url": "https://raw.githubusercontent.com/Orz-3/mini/master/Alpha/Kache.png"},
    {"name": "Kafka", "url": "https://raw.githubusercontent.com/Orz-3/mini/master/Alpha/Kafka.png"},
    {"name": "Kedou", "url": "https://raw.githubusercontent.com/Orz-3/mini/master/Alpha/Kedou.png"},
    {"name": "Kuai", "url": "https://raw.githubusercontent.com/Orz-3/mini/master/Alpha/Kuai.png"},
    {"name": "KuaiKan", "url": "https://raw.githubusercontent.com/Orz-3/mini/master/Alpha/KuaiKan.png"},
    {"name": "LINE-TV", "url": "https://raw.githubusercontent.com/Orz-3/mini/master/Alpha/LINE-TV.png"},
    {"name": "LT", "url": "https://raw.githubusercontent.com/Orz-3/mini/master/Alpha/LT.png"},
    {"name": "LV", "url": "https://raw.githubusercontent.com/Orz-3/mini/master/Alpha/LV.png"},
    {"name": "LiTV", "url": "https://raw.githubusercontent.com/Orz-3/mini/master/Alpha/LiTV.png"},
    {"name": "LiYing", "url": "https://raw.githubusercontent.com/Orz-3/mini/master/Alpha/LiYing.png"},
    {"name": "MDSS", "url": "https://raw.githubusercontent.com/Orz-3/mini/master/Alpha/MDSS.png"},
    {"name": "MGNB", "url": "https://raw.githubusercontent.com/Orz-3/mini/master/Alpha/MGNB.png"},
    {"name": "MO", "url": "https://raw.githubusercontent.com/Orz-3/mini/master/Alpha/MO.png"},
    {"name": "Maying", "url": "https://raw.githubusercontent.com/Orz-3/mini/master/Alpha/Maying.png"},
    {"name": "Miao", "url": "https://raw.githubusercontent.com/Orz-3/mini/master/Alpha/Miao.png"},
    {"name": "Mickey", "url": "https://raw.githubusercontent.com/Orz-3/mini/master/Alpha/Mickey.png"},
    {"name": "Microsoft", "url": "https://raw.githubusercontent.com/Orz-3/mini/master/Alpha/Microsoft.png"},
    {"name": "Mimemi", "url": "https://raw.githubusercontent.com/Orz-3/mini/master/Alpha/Mimemi.png"},
    {"name": "MovieCalendar", "url": "https://raw.githubusercontent.com/Orz-3/mini/master/Alpha/MovieCalendar.png"},
    {"name": "Muchang", "url": "https://raw.githubusercontent.com/Orz-3/mini/master/Alpha/Muchang.png"},
    {"name": "My5", "url": "https://raw.githubusercontent.com/Orz-3/mini/master/Alpha/My5.png"},
    {"name": "NL", "url": "https://raw.githubusercontent.com/Orz-3/mini/master/Alpha/NL.png"},
    {"name": "NOWLIVE", "url": "https://raw.githubusercontent.com/Orz-3/mini/master/Alpha/NOWLIVE.png"},
    {"name": "NSFW", "url": "https://raw.githubusercontent.com/Orz-3/mini/master/Alpha/NSFW.png"},
    {"name": "Naixue", "url": "https://raw.githubusercontent.com/Orz-3/mini/master/Alpha/Naixue.png"},
    {"name": "Netease", "url": "https://raw.githubusercontent.com/Orz-3/mini/master/Alpha/Netease.png"},
    {"name": "Netflix-W", "url": "https://raw.githubusercontent.com/Orz-3/mini/master/Alpha/Netflix-W.png"},
    {"name": "Netflix", "url": "https://raw.githubusercontent.com/Orz-3/mini/master/Alpha/Netflix.png"},
    {"name": "Nex", "url": "https://raw.githubusercontent.com/Orz-3/mini/master/Alpha/Nex.png"},
    {"name": "Now-E", "url": "https://raw.githubusercontent.com/Orz-3/mini/master/Alpha/Now-E.png"},
    {"name": "Np", "url": "https://raw.githubusercontent.com/Orz-3/mini/master/Alpha/Np.png"},
    {"name": "Nucleus", "url": "https://raw.githubusercontent.com/Orz-3/mini/master/Alpha/Nucleus.png"},
    {"name": "Oclean", "url": "https://raw.githubusercontent.com/Orz-3/mini/master/Alpha/Oclean.png"},
    {"name": "OneDrive", "url": "https://raw.githubusercontent.com/Orz-3/mini/master/Alpha/OneDrive.png"},
    {"name": "Oracle", "url": "https://raw.githubusercontent.com/Orz-3/mini/master/Alpha/Oracle.png"},
    {"name": "Orz", "url": "https://raw.githubusercontent.com/Orz-3/mini/master/Alpha/Orz.png"},
    {"name": "OvO", "url": "https://raw.githubusercontent.com/Orz-3/mini/master/Alpha/OvO.png"},
    {"name": "PBS", "url": "https://raw.githubusercontent.com/Orz-3/mini/master/Alpha/PBS.png"},
    {"name": "PH", "url": "https://raw.githubusercontent.com/Orz-3/mini/master/Alpha/PH.png"},
    {"name": "PL", "url": "https://raw.githubusercontent.com/Orz-3/mini/master/Alpha/PL.png"},
    {"name": "PSN", "url": "https://raw.githubusercontent.com/Orz-3/mini/master/Alpha/PSN.png"},
    {"name": "Pacifique", "url": "https://raw.githubusercontent.com/Orz-3/mini/master/Alpha/Pacifique.png"},
    {"name": "Pandora", "url": "https://raw.githubusercontent.com/Orz-3/mini/master/Alpha/Pandora.png"},
    {"name": "Paoluz", "url": "https://raw.githubusercontent.com/Orz-3/mini/master/Alpha/Paoluz.png"},
    {"name": "Paypal", "url": "https://raw.githubusercontent.com/Orz-3/mini/master/Alpha/Paypal.png"},
    {"name": "Personal", "url": "https://raw.githubusercontent.com/Orz-3/mini/master/Alpha/Personal.png"},
    {"name": "Piao", "url": "https://raw.githubusercontent.com/Orz-3/mini/master/Alpha/Piao.png"},
    {"name": "Pornhub-W", "url": "https://raw.githubusercontent.com/Orz-3/mini/master/Alpha/Pornhub-W.png"},
    {"name": "Pornhub", "url": "https://raw.githubusercontent.com/Orz-3/mini/master/Alpha/Pornhub.png"},
    {"name": "Prime-Video", "url": "https://raw.githubusercontent.com/Orz-3/mini/master/Alpha/Prime-Video.png"},
    {"name": "Privacy", "url": "https://raw.githubusercontent.com/Orz-3/mini/master/Alpha/Privacy.png"},
    {"name": "Prpr", "url": "https://raw.githubusercontent.com/Orz-3/mini/master/Alpha/Prpr.png"},
    {"name": "QQ", "url": "https://raw.githubusercontent.com/Orz-3/mini/master/Alpha/QQ.png"},
    {"name": "QQRead", "url": "https://raw.githubusercontent.com/Orz-3/mini/master/Alpha/QQRead.png"},
    {"name": "RIP", "url": "https://raw.githubusercontent.com/Orz-3/mini/master/Alpha/RIP.png"},
    {"name": "RU", "url": "https://raw.githubusercontent.com/Orz-3/mini/master/Alpha/RU.png"},
    {"name": "Renzhe", "url": "https://raw.githubusercontent.com/Orz-3/mini/master/Alpha/Renzhe.png"},
    {"name": "Rookie", "url": "https://raw.githubusercontent.com/Orz-3/mini/master/Alpha/Rookie.png"},
    {"name": "SCTC", "url": "https://raw.githubusercontent.com/Orz-3/mini/master/Alpha/SCTC.png"},
    {"name": "SE", "url": "https://raw.githubusercontent.com/Orz-3/mini/master/Alpha/SE.png"},
    {"name": "SG", "url": "https://raw.githubusercontent.com/Orz-3/mini/master/Alpha/SG.png"},
    {"name": "SONY", "url": "https://raw.githubusercontent.com/Orz-3/mini/master/Alpha/SONY.png"},
    {"name": "SS", "url": "https://raw.githubusercontent.com/Orz-3/mini/master/Alpha/SS.png"},
    {"name": "SSR", "url": "https://raw.githubusercontent.com/Orz-3/mini/master/Alpha/SSR.png"},
    {"name": "SSlinks", "url": "https://raw.githubusercontent.com/Orz-3/mini/master/Alpha/SSlinks.png"},
    {"name": "STC", "url": "https://raw.githubusercontent.com/Orz-3/mini/master/Alpha/STC.png"},
    {"name": "SWCloud", "url": "https://raw.githubusercontent.com/Orz-3/mini/master/Alpha/SWCloud.png"},
    {"name": "SaySS", "url": "https://raw.githubusercontent.com/Orz-3/mini/master/Alpha/SaySS.png"},
    {"name": "Scholar", "url": "https://raw.githubusercontent.com/Orz-3/mini/master/Alpha/Scholar.png"},
    {"name": "Shandian", "url": "https://raw.githubusercontent.com/Orz-3/mini/master/Alpha/Shandian.png"},
    {"name": "Situ", "url": "https://raw.githubusercontent.com/Orz-3/mini/master/Alpha/Situ.png"},
    {"name": "Skicat", "url": "https://raw.githubusercontent.com/Orz-3/mini/master/Alpha/Skicat.png"},
    {"name": "Socloud", "url": "https://raw.githubusercontent.com/Orz-3/mini/master/Alpha/Socloud.png"},
    {"name": "SoundCloud", "url": "https://raw.githubusercontent.com/Orz-3/mini/master/Alpha/SoundCloud.png"},
    {"name": "Spotify", "url": "https://raw.githubusercontent.com/Orz-3/mini/master/Alpha/Spotify.png"},
    {"name": "Ssp", "url": "https://raw.githubusercontent.com/Orz-3/mini/master/Alpha/Ssp.png"},
    {"name": "Streaming", "url": "https://raw.githubusercontent.com/Orz-3/mini/master/Alpha/Streaming.png"},
    {"name": "StreamingCN", "url": "https://raw.githubusercontent.com/Orz-3/mini/master/Alpha/StreamingCN.png"},
    {"name": "StreamingSE", "url": "https://raw.githubusercontent.com/Orz-3/mini/master/Alpha/StreamingSE.png"},
    {"name": "Suda", "url": "https://raw.githubusercontent.com/Orz-3/mini/master/Alpha/Suda.png"},
    {"name": "Sun", "url": "https://raw.githubusercontent.com/Orz-3/mini/master/Alpha/Sun.png"},
    {"name": "TH", "url": "https://raw.githubusercontent.com/Orz-3/mini/master/Alpha/TH.png"},
    {"name": "TIDAL", "url": "https://raw.githubusercontent.com/Orz-3/mini/master/Alpha/TIDAL.png"},
    {"name": "TR", "url": "https://raw.githubusercontent.com/Orz-3/mini/master/Alpha/TR.png"},
    {"name": "TW", "url": "https://raw.githubusercontent.com/Orz-3/mini/master/Alpha/TW.png"},
    {"name": "TaiWanGood", "url": "https://raw.githubusercontent.com/Orz-3/mini/master/Alpha/TaiWanGood.png"},
    {"name": "Team", "url": "https://raw.githubusercontent.com/Orz-3/mini/master/Alpha/Team.png"},
    {"name": "Telegram", "url": "https://raw.githubusercontent.com/Orz-3/mini/master/Alpha/Telegram.png"},
    {"name": "Thunder", "url": "https://raw.githubusercontent.com/Orz-3/mini/master/Alpha/Thunder.png"},
    {"name": "TikTok", "url": "https://raw.githubusercontent.com/Orz-3/mini/master/Alpha/TikTok.png"},
    {"name": "Touhou", "url": "https://raw.githubusercontent.com/Orz-3/mini/master/Alpha/Touhou.png"},
    {"name": "Trojan", "url": "https://raw.githubusercontent.com/Orz-3/mini/master/Alpha/Trojan.png"},
    {"name": "Twich", "url": "https://raw.githubusercontent.com/Orz-3/mini/master/Alpha/Twich.png"},
    {"name": "Twitter", "url": "https://raw.githubusercontent.com/Orz-3/mini/master/Alpha/Twitter.png"},
    {"name": "UA", "url": "https://raw.githubusercontent.com/Orz-3/mini/master/Alpha/UA.png"},
    {"name": "UK", "url": "https://raw.githubusercontent.com/Orz-3/mini/master/Alpha/UK.png"},
    {"name": "UN", "url": "https://raw.githubusercontent.com/Orz-3/mini/master/Alpha/UN.png"},
    {"name": "US", "url": "https://raw.githubusercontent.com/Orz-3/mini/master/Alpha/US.png"},
    {"name": "Unicorn", "url": "https://raw.githubusercontent.com/Orz-3/mini/master/Alpha/Unicorn.png"},
    {"name": "Unlocked", "url": "https://raw.githubusercontent.com/Orz-3/mini/master/Alpha/Unlocked.png"},
    {"name": "V2ray", "url": "https://raw.githubusercontent.com/Orz-3/mini/master/Alpha/V2ray.png"},
    {"name": "V2tun", "url": "https://raw.githubusercontent.com/Orz-3/mini/master/Alpha/V2tun.png"},
    {"name": "VN", "url": "https://raw.githubusercontent.com/Orz-3/mini/master/Alpha/VN.png"},
    {"name": "ViuTV", "url": "https://raw.githubusercontent.com/Orz-3/mini/master/Alpha/ViuTV.png"},
    {"name": "Vpn", "url": "https://raw.githubusercontent.com/Orz-3/mini/master/Alpha/Vpn.png"},
    {"name": "Vultr", "url": "https://raw.githubusercontent.com/Orz-3/mini/master/Alpha/Vultr.png"},
    {"name": "WIFI", "url": "https://raw.githubusercontent.com/Orz-3/mini/master/Alpha/WIFI.png"},
    {"name": "Wallless", "url": "https://raw.githubusercontent.com/Orz-3/mini/master/Alpha/Wallless.png"},
    {"name": "WestData", "url": "https://raw.githubusercontent.com/Orz-3/mini/master/Alpha/WestData.png"},
    {"name": "XTunnel", "url": "https://raw.githubusercontent.com/Orz-3/mini/master/Alpha/XTunnel.png"},
    {"name": "Xair", "url": "https://raw.githubusercontent.com/Orz-3/mini/master/Alpha/Xair.png"},
    {"name": "Xingmeng", "url": "https://raw.githubusercontent.com/Orz-3/mini/master/Alpha/Xingmeng.png"},
    {"name": "YK", "url": "https://raw.githubusercontent.com/Orz-3/mini/master/Alpha/YK.png"},
    {"name": "YouTube-W", "url": "https://raw.githubusercontent.com/Orz-3/mini/master/Alpha/YouTube-W.png"},
    {"name": "YouTube", "url": "https://raw.githubusercontent.com/Orz-3/mini/master/Alpha/YouTube.png"},
    {"name": "Ytoo", "url": "https://raw.githubusercontent.com/Orz-3/mini/master/Alpha/Ytoo.png"},
    {"name": "Yunyi", "url": "https://raw.githubusercontent.com/Orz-3/mini/master/Alpha/Yunyi.png"},
    {"name": "Ywhl", "url": "https://raw.githubusercontent.com/Orz-3/mini/master/Alpha/Ywhl.png"},
    {"name": "ZA", "url": "https://raw.githubusercontent.com/Orz-3/mini/master/Alpha/ZA.png"},
    {"name": "ZMTeacher", "url": "https://raw.githubusercontent.com/Orz-3/mini/master/Alpha/ZMTeacher.png"},
    {"name": "Zhs", "url": "https://raw.githubusercontent.com/Orz-3/mini/master/Alpha/Zhs.png"},
    {"name": "acfun", "url": "https://raw.githubusercontent.com/Orz-3/mini/master/Alpha/acfun.png"},
    {"name": "airport", "url": "https://raw.githubusercontent.com/Orz-3/mini/master/Alpha/airport.png"},
    {"name": "alipay", "url": "https://raw.githubusercontent.com/Orz-3/mini/master/Alpha/alipay.png"},
    {"name": "angelalign", "url": "https://raw.githubusercontent.com/Orz-3/mini/master/Alpha/angelalign.png"}
  ]
}

